torchapp/__init__.py
torchapp/apps.py
torchapp/bibtex/optuna.bib
torchapp/bibtex/skopt.bib
torchapp/bibtex/torchapp.bib
torchapp/bibtex/wandb.bib
torchapp/callbacks.py
torchapp/citations.py
torchapp/cli.py
torchapp/cookiecutter/.git
torchapp/cookiecutter/.github/ISSUE_TEMPLATE/bug_report.md
torchapp/cookiecutter/.github/ISSUE_TEMPLATE/feature_request.md
torchapp/cookiecutter/.github/workflows/testing.yml
torchapp/cookiecutter/.pytest_cache/.gitignore
torchapp/cookiecutter/.pytest_cache/CACHEDIR.TAG
torchapp/cookiecutter/.pytest_cache/README.md
torchapp/cookiecutter/.pytest_cache/v/cache/nodeids
torchapp/cookiecutter/.pytest_cache/v/cache/stepwise
torchapp/cookiecutter/CODE_OF_CONDUCT.md
torchapp/cookiecutter/CONTRIBUTING.rst
torchapp/cookiecutter/LICENSE
torchapp/cookiecutter/README.rst
torchapp/cookiecutter/cookiecutter.json
torchapp/cookiecutter/poetry.lock
torchapp/cookiecutter/pyproject.toml
torchapp/cookiecutter/tests/__init__.py
torchapp/cookiecutter/tests/test_cookiecutter.py
torchapp/cookiecutter/{{cookiecutter.project_slug}}/.coveragerc
torchapp/cookiecutter/{{cookiecutter.project_slug}}/.github/ISSUE_TEMPLATE/bug_report.md
torchapp/cookiecutter/{{cookiecutter.project_slug}}/.github/ISSUE_TEMPLATE/feature_request.md
torchapp/cookiecutter/{{cookiecutter.project_slug}}/.github/workflows/docs.yml
torchapp/cookiecutter/{{cookiecutter.project_slug}}/.github/workflows/publish.yml
torchapp/cookiecutter/{{cookiecutter.project_slug}}/.github/workflows/testing.yml
torchapp/cookiecutter/{{cookiecutter.project_slug}}/.gitignore
torchapp/cookiecutter/{{cookiecutter.project_slug}}/.gitlab-ci.yml
torchapp/cookiecutter/{{cookiecutter.project_slug}}/.pre-commit-config.yaml
torchapp/cookiecutter/{{cookiecutter.project_slug}}/CODE_OF_CONDUCT.md
torchapp/cookiecutter/{{cookiecutter.project_slug}}/CONTRIBUTING.rst
torchapp/cookiecutter/{{cookiecutter.project_slug}}/LICENSE
torchapp/cookiecutter/{{cookiecutter.project_slug}}/README.rst
torchapp-0.5.7.dist-info/LICENSE
torchapp-0.5.7.dist-info/METADATA
torchapp-0.5.7.dist-info/WHEEL
torchapp-0.5.7.dist-info/entry_points.txt
torchapp-0.5.7.dist-info/RECORD
