Metadata-Version: 2.3
Name: torchapp
Version: 0.5.7
Summary: A wrapper for PyTorch projects to create easy command-line interfaces and manage hyper-parameter tuning.
License: Apache-2.0
Keywords: PyTorch,pytorch,deep learning,command-line interface
Author: Robert Turnbull
Author-email: robert.turnbull@unimelb.edu.au
Requires-Python: >=3.10,<3.13
Classifier: Intended Audience :: Science/Research
Classifier: License :: OSI Approved :: Apache Software License
Classifier: Programming Language :: Python :: 3
Classifier: Programming Language :: Python :: 3.10
Classifier: Programming Language :: Python :: 3.11
Classifier: Programming Language :: Python :: 3.12
Classifier: Topic :: Scientific/Engineering :: Artificial Intelligence
Classifier: Topic :: Software Development :: Libraries :: Application Frameworks
Classifier: Topic :: Software Development :: Libraries :: Python Modules
Requires-Dist: Pillow (>=9.0.1)
Requires-Dist: PyYAML (>=6.0)
Requires-Dist: appdirs (>=1.4.4)
Requires-Dist: cmaes (>=0.11.1)
Requires-Dist: cookiecutter (>=2.1.1)
Requires-Dist: executing (>=2.0.1)
Requires-Dist: lightning (>=2.3.3)
Requires-Dist: numpy (>=1.22.0,<2.0.0)
Requires-Dist: optuna (>=2.10.0)
Requires-Dist: pandas (>=1.3.5)
Requires-Dist: pybtex (>=0.24.0)
Requires-Dist: pybtexnbib (>=0.1.1)
Requires-Dist: pyjwt (>=2.4.0)
Requires-Dist: rich (>=10.16.1)
Requires-Dist: scikit-learn (>=1.0.2)
Requires-Dist: scikit-optimize (>=0.9.0)
Requires-Dist: scipy (>=1.9.1)
Requires-Dist: torch (>=1.12.1)
Requires-Dist: torchvision (>=0.13.0)
Requires-Dist: typer (>=0.4.0)
Requires-Dist: wandb (>=0.12.9)
Project-URL: Documentation, https://rbturnbull.github.io/torchapp/
Project-URL: Homepage, https://github.com/rbturnbull/torchapp
Project-URL: Repository, https://github.com/rbturnbull/torchapp
